fr_db/__init__.py
fr_db/models/__init__.py
fr_db/models/actual_shift.py
fr_db/models/auth_session.py
fr_db/models/base.py
fr_db/models/base_user.py
fr_db/models/company.py
fr_db/models/customer.py
fr_db/models/department.py
fr_db/models/employee.py
fr_db/models/gate.py
fr_db/models/gate_user.py
fr_db/models/image.py
fr_db/models/links.py
fr_db/models/mixins.py
fr_db/models/photo.py
fr_db/models/photo_vector.py
fr_db/models/planned_shift.py
fr_db/models/recogn_assoc.py
fr_db/models/recognition.py
fr_db/models/refresh_token.py
fr_db/models/shift_mixin.py
fr_db/models/tg_user.py
fr_db/models/user.py
fr_db/models/vectorizeable.py
fr_db/py.typed
fr_db-0.1.2.dist-info/METADATA
fr_db-0.1.2.dist-info/WHEEL
fr_db-0.1.2.dist-info/RECORD
