Metadata-Version: 2.1
Name: fr_db
Version: 0.1.2
Summary: 
Author: artur lagunov
Author-email: lagunovartur@inbox.ru
Requires-Python: >=3.11,<4.0
Classifier: Programming Language :: Python :: 3
Classifier: Programming Language :: Python :: 3.11
Classifier: Programming Language :: Python :: 3.12
Requires-Dist: alembic (>=1.13.3,<2.0.0)
Requires-Dist: asyncpg (>=0.30.0,<0.31.0)
Requires-Dist: attrs (>=24.2.0,<25.0.0)
Requires-Dist: dishka (>=1.3.0,<2.0.0)
Requires-Dist: fr-common-lib (>=0.4.0,<0.5.0)
Requires-Dist: pydantic (>=2.9.2,<3.0.0)
Requires-Dist: pydantic-settings (>=2.6.0,<3.0.0)
